{
  "headers": {
    "content-length": "293",
    "set-cookie": "__cfduid=d223f77b40c5c0b33bcb6c9437a431a951610353226; expires=Wed, 10-Feb-21 08:20:26 GMT; path=/; domain=.deno.land; HttpOnly; SameSite=Lax; Secure",
    "x-amz-version-id": "IN.TKJ4owKnN946NY7tHFemty4y0g049",
    "x-amz-request-id": "2FC9FFA771128A20",
    "date": "Mon, 11 Jan 2021 08:20:26 GMT",
    "cf-request-id": "0792214a37000015fc673c2000000001",
    "etag": "\"fffb229ce033b7fd2b852c6a62d9bf90\"",
    "expect-ct": "max-age=604800, report-uri=\"https://report-uri.cloudflare.com/cdn-cgi/beacon/expect-ct\"",
    "server": "cloudflare",
    "cf-ray": "60fd37f05a0f15fc-ARN",
    "cache-control": "public, max-age=31536000, immutable",
    "content-type": "application/typescript; charset=utf-8",
    "access-control-allow-origin": "*",
    "nel": "{\"report_to\":\"cf-nel\",\"max_age\":604800}",
    "vary": "Accept-Encoding",
    "accept-ranges": "bytes",
    "x-amz-id-2": "3eXAKobS67JUOu2rVSrBWnU/Y94aC3cfZndcmp1PASwu2HRAQrqwYyH/fZbMOBD+1OStcUT4/d4=",
    "cf-cache-status": "MISS",
    "report-to": "{\"endpoints\":[{\"url\":\"https:\\/\\/a.nel.cloudflare.com\\/report?s=VD8bQxWExtFrD9vPmCEC5PFQmgEXkazxD29JVOnXTj2RU%2FoXD5916%2BAUd21zgsE%2BY53g2UDWcTtgwAe0k4TBxFFObvHV4dqAzNY%3D\"}],\"group\":\"cf-nel\",\"max_age\":604800}",
    "last-modified": "Wed, 30 Dec 2020 15:14:32 GMT"
  },
  "url": "https://deno.land/std@0.83.0/hash/hasher.ts"
}