{
  "headers": {
    "strict-transport-security": "max-age=31536000",
    "content-type": "text/plain; charset=utf-8",
    "x-xss-protection": "1; mode=block",
    "content-security-policy": "default-src 'none'; style-src 'unsafe-inline'; sandbox",
    "x-github-request-id": "9F92:26AB:9CFFBB:AD25DD:60461595",
    "x-content-type-options": "nosniff",
    "accept-ranges": "bytes",
    "x-served-by": "cache-osl6522-OSL",
    "date": "Mon, 08 Mar 2021 13:45:49 GMT",
    "access-control-allow-origin": "*",
    "x-cache": "HIT",
    "source-age": "9",
    "vary": "Authorization,Accept-Encoding",
    "x-frame-options": "deny",
    "etag": "W/\"114b958a5bc24260cbe14682fe74bb0ce95713c016d523d94d7b75273d7a2ce7\"",
    "x-fastly-request-id": "6bdf125facdecb92e217babe381aa10307a21979",
    "x-cache-hits": "1",
    "x-timer": "S1615211149.313777,VS0,VE0",
    "cache-control": "max-age=300",
    "expires": "Mon, 08 Mar 2021 13:50:49 GMT",
    "via": "1.1 varnish"
  },
  "url": "https://raw.githubusercontent.com/trgwii/bundler/master/types.ts"
}